pd_df_str/__init__.py
pd_df_str/pd_df_str.py
pd_df_str-1.0.0.dist-info/LICENSE
pd_df_str-1.0.0.dist-info/METADATA
pd_df_str-1.0.0.dist-info/WHEEL
pd_df_str-1.0.0.dist-info/top_level.txt
pd_df_str-1.0.0.dist-info/RECORD
