Metadata-Version: 2.1
Name: pd-df-str
Version: 1.0.0
Summary: Extends `pandas.Series.str` methods so that they can be applied to `pandas.DataFrame` objects by registering a custom accessor.
Author-email: "Andrés G. Delannoy" <andres.delannoy@gmail.com>
License: MIT License
Project-URL: Homepage, https://github.com/delannoy/pd_df_str
Keywords: pandas,dataframe,str
Classifier: License :: OSI Approved :: MIT License
Classifier: Programming Language :: Python
Classifier: Programming Language :: Python :: 3
Classifier: Topic :: Text Processing
Classifier: Topic :: Text Processing :: General
Requires-Python: >=3.7
License-File: LICENSE
Requires-Dist: pandas (>=0.25.0)
